bearsharkutils
