Metadata-Version: 2.1
Name: bearsharkutils
Version: 1.0.3
Summary: My package for easier work with pygame
Home-page: https://github.com/BearShark-8bit/bearsharkutils
Download-URL: https://github.com/BearShark-8bit/bearsharkutils/archive/refs/tags/v1.0.0.tar.gz
Author: Roman Semeniuk
Author-email: rcemeniuk@gmail.com
License: MIT
Classifier: License :: OSI Approved :: MIT License
License-File: LICENCE
